copyhere/__init__.py
copyhere/__main__.py
copyhere-1.1.5.dist-info/LICENSE
copyhere-1.1.5.dist-info/METADATA
copyhere-1.1.5.dist-info/WHEEL
copyhere-1.1.5.dist-info/top_level.txt
copyhere-1.1.5.dist-info/RECORD
