Metadata-Version: 2.1
Name: copyhere
Version: 1.1.5
Summary: Module for copy or unzip a file to cwd
Home-page: https://github.com/an-dr/copyhere
Author: Andrei Gramakov
Author-email: mail@agramakov.me
License: MIT
Platform: UNKNOWN
Requires-Python: >=3
Requires-Dist: easygui
